mpl_sphinx_theme/__init__.py
mpl_sphinx_theme/_version.py
mpl_sphinx_theme/donate_sidebar.html
mpl_sphinx_theme/mpl_icon_links.html
mpl_sphinx_theme/mpl_nav_bar.html
mpl_sphinx_theme/theme.conf
mpl_sphinx_theme/components/doc_version.html
mpl_sphinx_theme/static/logo_dark.svg
mpl_sphinx_theme/static/logo_light.svg
mpl_sphinx_theme/static/css/style.css
mpl_sphinx_theme/static/images/favicon.ico
mpl_sphinx_theme-3.10.0.dist-info/licenses/LICENSE.txt
mpl_sphinx_theme-3.10.0.dist-info/METADATA
mpl_sphinx_theme-3.10.0.dist-info/WHEEL
mpl_sphinx_theme-3.10.0.dist-info/entry_points.txt
mpl_sphinx_theme-3.10.0.dist-info/top_level.txt
mpl_sphinx_theme-3.10.0.dist-info/RECORD
