Metadata-Version: 2.4
Name: mpl_sphinx_theme
Version: 3.10.0
Summary: Matplotlib theme for Sphinx
Author: Matplotlib Developers
License: BSD 3-Clause License
Project-URL: homepage, https://matplotlib.org/mpl-sphinx-theme/
Project-URL: repository, https://github.com/matplotlib/mpl-sphinx-theme
Classifier: Framework :: Sphinx :: Theme
Classifier: Programming Language :: Python :: 3 :: Only
Classifier: Topic :: Documentation
Classifier: Topic :: Documentation :: Sphinx
Requires-Python: >=3
License-File: LICENSE.txt
Requires-Dist: pydata-sphinx-theme==0.16.1
Requires-Dist: matplotlib
Requires-Dist: sphinx-design
Dynamic: license-file
